django_firefly_tasks/__init__.py
django_firefly_tasks/admin.py
django_firefly_tasks/apps.py
django_firefly_tasks/decorators.py
django_firefly_tasks/exceptions.py
django_firefly_tasks/models.py
django_firefly_tasks/utils.py
django_firefly_tasks/views.py
django_firefly_tasks/_private/__init__.py
django_firefly_tasks/_private/consts.py
django_firefly_tasks/_private/consumers.py
django_firefly_tasks/_private/processors.py
django_firefly_tasks/_private/utils.py
django_firefly_tasks/management/__init__.py
django_firefly_tasks/management/commands/__init__.py
django_firefly_tasks/management/commands/consume_tasks.py
django_firefly_tasks/management/commands/delete_completed_tasks.py
django_firefly_tasks/management/commands/delete_failed_tasks.py
django_firefly_tasks/management/commands/mark_failed_tasks_consumable.py
django_firefly_tasks/migrations/0001_initial.py
django_firefly_tasks/migrations/__init__.py
django_firefly_tasks-0.4.0.dist-info/licenses/LICENSE
django_firefly_tasks-0.4.0.dist-info/METADATA
django_firefly_tasks-0.4.0.dist-info/WHEEL
django_firefly_tasks-0.4.0.dist-info/top_level.txt
django_firefly_tasks-0.4.0.dist-info/RECORD
