Metadata-Version: 2.4
Name: django_firefly_tasks
Version: 0.4.0
Summary: Simple and easy to use background tasks in Django without dependencies!
Author-email: Łukasz Klim <lukasz.klim92@gmail.com>
Project-URL: Homepage, https://github.com/lukas346/django_firefly_tasks
Project-URL: Documentation, https://lukas346.github.io/django_firefly_tasks/
Project-URL: Issues, https://github.com/lukas346/django_firefly_tasks/issues
Classifier: Programming Language :: Python :: 3
Classifier: Programming Language :: Python :: 3.10
Classifier: Programming Language :: Python :: 3.11
Classifier: Programming Language :: Python :: 3.12
Classifier: Programming Language :: Python :: 3.13
Classifier: Operating System :: OS Independent
Classifier: Framework :: Django :: 4.2
Classifier: Framework :: Django :: 5.2
Requires-Python: <3.14,>=3.10
License-File: LICENSE
Requires-Dist: Django>=4.2
Dynamic: license-file
